any_guardrail/__init__.py
any_guardrail/api.py
any_guardrail/base.py
any_guardrail/types.py
any_guardrail/guardrails/__init__.py
any_guardrail/guardrails/huggingface.py
any_guardrail/guardrails/alinia/__init__.py
any_guardrail/guardrails/alinia/alinia.py
any_guardrail/guardrails/any_llm/__init__.py
any_guardrail/guardrails/any_llm/any_llm.py
any_guardrail/guardrails/azure_content_safety/__init__.py
any_guardrail/guardrails/azure_content_safety/azure_content_safety.py
any_guardrail/guardrails/deepset/__init__.py
any_guardrail/guardrails/deepset/deepset.py
any_guardrail/guardrails/duo_guard/__init__.py
any_guardrail/guardrails/duo_guard/duo_guard.py
any_guardrail/guardrails/flowjudge/__init__.py
any_guardrail/guardrails/flowjudge/flowjudge.py
any_guardrail/guardrails/glider/__init__.py
any_guardrail/guardrails/glider/glider.py
any_guardrail/guardrails/harm_guard/__init__.py
any_guardrail/guardrails/harm_guard/harm_guard.py
any_guardrail/guardrails/injec_guard/__init__.py
any_guardrail/guardrails/injec_guard/injec_guard.py
any_guardrail/guardrails/jasper/__init__.py
any_guardrail/guardrails/jasper/jasper.py
any_guardrail/guardrails/llama_guard/__init__.py
any_guardrail/guardrails/llama_guard/llama_guard.py
any_guardrail/guardrails/off_topic/__init__.py
any_guardrail/guardrails/off_topic/off_topic.py
any_guardrail/guardrails/off_topic/off_topic_jina.py
any_guardrail/guardrails/off_topic/off_topic_stsb.py
any_guardrail/guardrails/off_topic/models/cross_encoder_mlp.py
any_guardrail/guardrails/off_topic/models/cross_encoder_shared.py
any_guardrail/guardrails/pangolin/__init__.py
any_guardrail/guardrails/pangolin/pangolin.py
any_guardrail/guardrails/protectai/__init__.py
any_guardrail/guardrails/protectai/protectai.py
any_guardrail/guardrails/sentinel/__init__.py
any_guardrail/guardrails/sentinel/sentinel.py
any_guardrail/guardrails/shield_gemma/__init__.py
any_guardrail/guardrails/shield_gemma/shield_gemma.py
any_guardrail-0.3.1.dist-info/licenses/LICENSE
any_guardrail-0.3.1.dist-info/METADATA
any_guardrail-0.3.1.dist-info/WHEEL
any_guardrail-0.3.1.dist-info/top_level.txt
any_guardrail-0.3.1.dist-info/RECORD
