Metadata-Version: 2.4
Name: any-guardrail
Version: 0.3.1
License: Apache-2.0
Project-URL: Documentation, https://mozilla-ai.github.io/any-guardrail/
Project-URL: Issues, https://github.com/mozilla-ai/any-guardrail/issues
Project-URL: Source, https://github.com/mozilla-ai/any-guardrail
Requires-Python: >=3.11
License-File: LICENSE
Requires-Dist: any-llm-sdk>=1.7.0
Requires-Dist: pydantic
Provides-Extra: all
Requires-Dist: any-guardrail[azure-content-safety,flowjudge,huggingface]; extra == "all"
Provides-Extra: flowjudge
Requires-Dist: flow-judge[hf]>=0.1.2; extra == "flowjudge"
Provides-Extra: huggingface
Requires-Dist: huggingface-hub>=0.33.4; extra == "huggingface"
Requires-Dist: transformers>=4.53.2; extra == "huggingface"
Requires-Dist: torch>=2.7.1; extra == "huggingface"
Requires-Dist: hf-xet>=1.1.5; extra == "huggingface"
Provides-Extra: azure-content-safety
Requires-Dist: azure-ai-contentsafety>=1.0.0; extra == "azure-content-safety"
Requires-Dist: pathvalidate>=3.3.1; extra == "azure-content-safety"
Dynamic: license-file
